aiforge/__init__.py
aiforges-0.0.0.dist-info/METADATA
aiforges-0.0.0.dist-info/WHEEL
aiforges-0.0.0.dist-info/top_level.txt
aiforges-0.0.0.dist-info/RECORD
